{
  "KBIS": {
    "o3": 23,
    "pm25": 24,
    "pm10": 9,
    "aqi": 24
  },
  "KBOS": {
    "o3": 0,
    "pm25": 38,
    "pm10": 8,
    "aqi": 38
  },
  "KDFW": {
    "o3": 26,
    "aqi": 26
  },
  "KDEN": {
    "o3": 39,
    "pm25": 44,
    "pm10": 22,
    "aqi": 44
  },
  "KLAX": {
    "o3": 33,
    "pm25": 68,
    "pm10": 20,
    "aqi": 68
  },
  "KMIA": {
    "o3": 27,
    "pm25": 27,
    "aqi": 27
  },
  "KOMA": {
    "o3": 19,
    "pm25": 39,
    "pm10": 19,
    "aqi": 39
  },
  "KORD": {
    "o3": 23,
    "pm25": 55,
    "pm10": 10,
    "aqi": 55
  },
  "KPDX": {
    "pm25": 39,
    "aqi": 39
  },
  "KPHX": {
    "o3": 58,
    "pm25": 82,
    "pm10": 44,
    "aqi": 82
  },
  "KTUS": {
    "o3": 45,
    "pm25": 59,
    "pm10": 39,
    "aqi": 59
  }
}