{
  "KBIS": {
    "o3": 33,
    "pm25": 15,
    "pm10": 0,
    "aqi": 33
  },
  "KBOS": {
    "o3": 20,
    "pm25": 67,
    "pm10": 25,
    "aqi": 67
  },
  "KDFW": {
    "o3": 28,
    "pm25": 54,
    "pm10": 18,
    "aqi": 54
  },
  "KDEN": {
    "o3": 32,
    "pm25": 44,
    "pm10": 36,
    "aqi": 44
  },
  "KLAX": {},
  "KMIA": {
    "o3": 39,
    "pm25": 43,
    "aqi": 43
  },
  "KOMA": {
    "o3": 23,
    "pm25": 35,
    "pm10": 18,
    "aqi": 35
  },
  "KORD": {
    "o3": 36,
    "pm25": 21,
    "aqi": 36
  },
  "KPDX": {
    "pm25": 32,
    "aqi": 32
  },
  "KPHX": {
    "o3": 35,
    "pm25": 40,
    "pm10": 35,
    "aqi": 40
  },
  "KTUS": {
    "o3": 21,
    "pm25": 68,
    "pm10": 12,
    "aqi": 68
  }
}