{
  "KBIS": {
    "o3": 28,
    "pm25": 19,
    "pm10": 14,
    "aqi": 28
  },
  "KBOS": {
    "o3": 26,
    "pm25": 28,
    "pm10": 10,
    "aqi": 28
  },
  "KDFW": {
    "o3": 26,
    "pm25": 53,
    "pm10": 22,
    "aqi": 53
  },
  "KDEN": {
    "o3": 48,
    "pm25": 47,
    "pm10": 30,
    "aqi": 48
  },
  "KLAX": {},
  "KMIA": {
    "o3": 21,
    "pm25": 40,
    "aqi": 40
  },
  "KOMA": {
    "o3": 26,
    "pm25": 43,
    "pm10": 24,
    "aqi": 43
  },
  "KORD": {
    "o3": 71,
    "pm25": 62,
    "aqi": 71
  },
  "KPDX": {
    "pm25": 17,
    "aqi": 17
  },
  "KPHX": {
    "o3": 48,
    "pm25": 57,
    "pm10": 51,
    "aqi": 57
  },
  "KTUS": {
    "o3": 31,
    "pm25": 30,
    "pm10": 14,
    "aqi": 31
  }
}